rose/__init__.py
rose/_version.py
rose/snippets.py
pandas_rose-2023.8.0.dist-info/LICENSE
pandas_rose-2023.8.0.dist-info/METADATA
pandas_rose-2023.8.0.dist-info/WHEEL
pandas_rose-2023.8.0.dist-info/top_level.txt
pandas_rose-2023.8.0.dist-info/RECORD
