Metadata-Version: 2.1
Name: pandas-rose
Version: 2023.8.0
Summary: A simple Pandas accessor to make windrose plots.
Author-email: Brian Blaylock <blaylockbk@gmail.com>
Maintainer-email: Brian Blaylock <blaylockbk@gmail.com>
License: MIT License
Project-URL: Homepage, https://github.com/blaylockbk/pandas-rose
Project-URL: Documentation, https://github.com/blaylockbk/pandas-rose
Project-URL: Repository, https://github.com/blaylockbk/pandas-rose
Project-URL: Changelog, https://github.com/blaylockbk/pandas-rose/releases
Project-URL: Bug Tracker, https://github.com/blaylockbk/pandas-rose/issues
Keywords: weather,meteorology,wind
Classifier: Programming Language :: Python
Requires-Python: >=3.8
License-File: LICENSE
Requires-Dist: matplotlib
Requires-Dist: numpy
Requires-Dist: pandas
Provides-Extra: docs
Requires-Dist: mkdocs-material ; extra == 'docs'
Provides-Extra: test
Requires-Dist: pytest ; extra == 'test'
Requires-Dist: black ; extra == 'test'
